README.md
setup.py
biwkv4/__init__.py
biwkv4/biwkv4_cuda_new.cu
biwkv4/biwkv4_op_new.cpp
biwkv4_cuda.egg-info/PKG-INFO
biwkv4_cuda.egg-info/SOURCES.txt
biwkv4_cuda.egg-info/dependency_links.txt
biwkv4_cuda.egg-info/not-zip-safe
biwkv4_cuda.egg-info/requires.txt
biwkv4_cuda.egg-info/top_level.txt